{"title":"uniform-n400-r0-s-4301774886944954552-d3.0400","map_width":500,"map_height":500,"num_leaves":400,"parameters":{"tree_type":"circular","position_type":"sliding","color_distance":"leaves","interval_margin_rectangular":0.4,"interval_margin_circular":0.4,"aversion_centroid_ratio":0.1,"color_difference":0.3,"num_cycles":100,"allowed_outside_interval":false},"tree":{"leaf":false,"id":798,"left":{"leaf":false,"id":797,"left":{"leaf":false,"id":796,"left":{"leaf":false,"id":787,"left":{"leaf":false,"id":786,"left":{"leaf":false,"id":755,"left":{"leaf":false,"id":686,"left":{"leaf":false,"id":552,"left":{"leaf":true,"id":126,"label":"126","site_id":126},"right":{"leaf":false,"id":443,"left":{"leaf":true,"id":44,"label":"44","site_id":44},"right":{"leaf":true,"id":393,"label":"393","site_id":393}}},"right":{"leaf":false,"id":583,"left":{"leaf":false,"id":478,"left":{"leaf":false,"id":471,"left":{"leaf":false,"id":455,"left":{"leaf":true,"id":290,"label":"290","site_id":290},"right":{"leaf":true,"id":39,"label":"39","site_id":39}},"right":{"leaf":true,"id":302,"label":"302","site_id":302}},"right":{"leaf":true,"id":75,"label":"75","site_id":75}},"right":{"leaf":false,"id":500,"left":{"leaf":false,"id":407,"left":{"leaf":true,"id":146,"label":"146","site_id":146},"right":{"leaf":true,"id":158,"label":"158","site_id":158}},"right":{"leaf":true,"id":220,"label":"220","site_id":220}}}},"right":{"leaf":false,"id":734,"left":{"leaf":false,"id":715,"left":{"leaf":false,"id":604,"left":{"leaf":true,"id":127,"label":"127","site_id":127},"right":{"leaf":true,"id":240,"label":"240","site_id":240}},"right":{"leaf":false,"id":648,"left":{"leaf":false,"id":402,"left":{"leaf":true,"id":82,"label":"82","site_id":82},"right":{"leaf":true,"id":92,"label":"92","site_id":92}},"right":{"leaf":false,"id":606,"left":{"leaf":false,"id":601,"left":{"leaf":true,"id":292,"label":"292","site_id":292},"right":{"leaf":false,"id":487,"left":{"leaf":true,"id":226,"label":"226","site_id":226},"right":{"leaf":false,"id":483,"left":{"leaf":true,"id":262,"label":"262","site_id":262},"right":{"leaf":true,"id":198,"label":"198","site_id":198}}}},"right":{"leaf":false,"id":573,"left":{"leaf":true,"id":142,"label":"142","site_id":142},"right":{"leaf":false,"id":456,"left":{"leaf":true,"id":280,"label":"280","site_id":280},"right":{"leaf":true,"id":57,"label":"57","site_id":57}}}}}},"right":{"leaf":false,"id":724,"left":{"leaf":false,"id":595,"left":{"leaf":false,"id":418,"left":{"leaf":true,"id":264,"label":"264","site_id":264},"right":{"leaf":true,"id":363,"label":"363","site_id":363}},"right":{"leaf":false,"id":475,"left":{"leaf":true,"id":76,"label":"76","site_id":76},"right":{"leaf":true,"id":286,"label":"286","site_id":286}}},"right":{"leaf":false,"id":632,"left":{"leaf":false,"id":448,"left":{"leaf":false,"id":436,"left":{"leaf":true,"id":162,"label":"162","site_id":162},"right":{"leaf":true,"id":21,"label":"21","site_id":21}},"right":{"leaf":true,"id":245,"label":"245","site_id":245}},"right":{"leaf":false,"id":608,"left":{"leaf":true,"id":289,"label":"289","site_id":289},"right":{"leaf":false,"id":516,"left":{"leaf":false,"id":422,"left":{"leaf":true,"id":1,"label":"1","site_id":1},"right":{"leaf":true,"id":151,"label":"151","site_id":151}},"right":{"leaf":true,"id":352,"label":"352","site_id":352}}}}}}},"right":{"leaf":false,"id":783,"left":{"leaf":false,"id":781,"left":{"leaf":false,"id":780,"left":{"leaf":false,"id":760,"left":{"leaf":false,"id":738,"left":{"leaf":false,"id":731,"left":{"leaf":false,"id":718,"left":{"leaf":true,"id":117,"label":"117","site_id":117},"right":{"leaf":false,"id":558,"left":{"leaf":true,"id":225,"label":"225","site_id":225},"right":{"leaf":false,"id":431,"left":{"leaf":true,"id":320,"label":"320","site_id":320},"right":{"leaf":true,"id":388,"label":"388","site_id":388}}}},"right":{"leaf":false,"id":711,"left":{"leaf":false,"id":709,"left":{"leaf":false,"id":702,"left":{"leaf":false,"id":594,"left":{"leaf":false,"id":584,"left":{"leaf":false,"id":547,"left":{"leaf":false,"id":403,"left":{"leaf":true,"id":91,"label":"91","site_id":91},"right":{"leaf":true,"id":132,"label":"132","site_id":132}},"right":{"leaf":true,"id":154,"label":"154","site_id":154}},"right":{"leaf":true,"id":228,"label":"228","site_id":228}},"right":{"leaf":true,"id":374,"label":"374","site_id":374}},"right":{"leaf":false,"id":615,"left":{"leaf":false,"id":580,"left":{"leaf":false,"id":423,"left":{"leaf":true,"id":48,"label":"48","site_id":48},"right":{"leaf":true,"id":284,"label":"284","site_id":284}},"right":{"leaf":false,"id":537,"left":{"leaf":true,"id":6,"label":"6","site_id":6},"right":{"leaf":true,"id":331,"label":"331","site_id":331}}},"right":{"leaf":false,"id":605,"left":{"leaf":true,"id":278,"label":"278","site_id":278},"right":{"leaf":false,"id":528,"left":{"leaf":true,"id":379,"label":"379","site_id":379},"right":{"leaf":true,"id":221,"label":"221","site_id":221}}}}},"right":{"leaf":false,"id":707,"left":{"leaf":true,"id":7,"label":"7","site_id":7},"right":{"leaf":false,"id":447,"left":{"leaf":true,"id":219,"label":"219","site_id":219},"right":{"leaf":false,"id":438,"left":{"leaf":true,"id":399,"label":"399","site_id":399},"right":{"leaf":true,"id":304,"label":"304","site_id":304}}}}},"right":{"leaf":false,"id":463,"left":{"leaf":false,"id":452,"left":{"leaf":false,"id":416,"left":{"leaf":true,"id":136,"label":"136","site_id":136},"right":{"leaf":true,"id":84,"label":"84","site_id":84}},"right":{"leaf":true,"id":324,"label":"324","site_id":324}},"right":{"leaf":true,"id":340,"label":"340","site_id":340}}}},"right":{"leaf":false,"id":690,"left":{"leaf":false,"id":474,"left":{"leaf":true,"id":63,"label":"63","site_id":63},"right":{"leaf":true,"id":71,"label":"71","site_id":71}},"right":{"leaf":false,"id":482,"left":{"leaf":true,"id":223,"label":"223","site_id":223},"right":{"leaf":true,"id":139,"label":"139","site_id":139}}}},"right":{"leaf":true,"id":90,"label":"90","site_id":90}},"right":{"leaf":false,"id":765,"left":{"leaf":false,"id":762,"left":{"leaf":false,"id":681,"left":{"leaf":true,"id":391,"label":"391","site_id":391},"right":{"leaf":false,"id":506,"left":{"leaf":true,"id":339,"label":"339","site_id":339},"right":{"leaf":true,"id":135,"label":"135","site_id":135}}},"right":{"leaf":false,"id":736,"left":{"leaf":false,"id":616,"left":{"leaf":false,"id":600,"left":{"leaf":false,"id":465,"left":{"leaf":true,"id":143,"label":"143","site_id":143},"right":{"leaf":false,"id":464,"left":{"leaf":true,"id":134,"label":"134","site_id":134},"right":{"leaf":true,"id":326,"label":"326","site_id":326}}},"right":{"leaf":true,"id":316,"label":"316","site_id":316}},"right":{"leaf":true,"id":256,"label":"256","site_id":256}},"right":{"leaf":false,"id":538,"left":{"leaf":true,"id":181,"label":"181","site_id":181},"right":{"leaf":true,"id":159,"label":"159","site_id":159}}}},"right":{"leaf":false,"id":732,"left":{"leaf":false,"id":700,"left":{"leaf":false,"id":677,"left":{"leaf":false,"id":676,"left":{"leaf":false,"id":651,"left":{"leaf":true,"id":68,"label":"68","site_id":68},"right":{"leaf":false,"id":539,"left":{"leaf":true,"id":123,"label":"123","site_id":123},"right":{"leaf":true,"id":113,"label":"113","site_id":113}}},"right":{"leaf":false,"id":479,"left":{"leaf":true,"id":171,"label":"171","site_id":171},"right":{"leaf":false,"id":459,"left":{"leaf":true,"id":367,"label":"367","site_id":367},"right":{"leaf":false,"id":430,"left":{"leaf":true,"id":83,"label":"83","site_id":83},"right":{"leaf":true,"id":51,"label":"51","site_id":51}}}}},"right":{"leaf":false,"id":501,"left":{"leaf":true,"id":294,"label":"294","site_id":294},"right":{"leaf":false,"id":401,"left":{"leaf":true,"id":276,"label":"276","site_id":276},"right":{"leaf":true,"id":227,"label":"227","site_id":227}}}},"right":{"leaf":false,"id":642,"left":{"leaf":true,"id":155,"label":"155","site_id":155},"right":{"leaf":true,"id":265,"label":"265","site_id":265}}},"right":{"leaf":false,"id":705,"left":{"leaf":false,"id":536,"left":{"leaf":true,"id":201,"label":"201","site_id":201},"right":{"leaf":false,"id":499,"left":{"leaf":false,"id":493,"left":{"leaf":true,"id":345,"label":"345","site_id":345},"right":{"leaf":true,"id":383,"label":"383","site_id":383}},"right":{"leaf":false,"id":428,"left":{"leaf":true,"id":371,"label":"371","site_id":371},"right":{"leaf":true,"id":336,"label":"336","site_id":336}}}},"right":{"leaf":true,"id":381,"label":"381","site_id":381}}}}},"right":{"leaf":false,"id":735,"left":{"leaf":false,"id":727,"left":{"leaf":false,"id":663,"left":{"leaf":true,"id":318,"label":"318","site_id":318},"right":{"leaf":false,"id":490,"left":{"leaf":true,"id":277,"label":"277","site_id":277},"right":{"leaf":true,"id":24,"label":"24","site_id":24}}},"right":{"leaf":false,"id":723,"left":{"leaf":false,"id":701,"left":{"leaf":false,"id":420,"left":{"leaf":true,"id":247,"label":"247","site_id":247},"right":{"leaf":true,"id":338,"label":"338","site_id":338}},"right":{"leaf":true,"id":2,"label":"2","site_id":2}},"right":{"leaf":false,"id":570,"left":{"leaf":false,"id":449,"left":{"leaf":true,"id":56,"label":"56","site_id":56},"right":{"leaf":false,"id":410,"left":{"leaf":true,"id":178,"label":"178","site_id":178},"right":{"leaf":true,"id":386,"label":"386","site_id":386}}},"right":{"leaf":true,"id":5,"label":"5","site_id":5}}}},"right":{"leaf":false,"id":713,"left":{"leaf":true,"id":45,"label":"45","site_id":45},"right":{"leaf":false,"id":599,"left":{"leaf":false,"id":564,"left":{"leaf":true,"id":382,"label":"382","site_id":382},"right":{"leaf":true,"id":12,"label":"12","site_id":12}},"right":{"leaf":false,"id":440,"left":{"leaf":true,"id":250,"label":"250","site_id":250},"right":{"leaf":true,"id":180,"label":"180","site_id":180}}}}}},"right":{"leaf":false,"id":778,"left":{"leaf":false,"id":776,"left":{"leaf":false,"id":759,"left":{"leaf":false,"id":756,"left":{"leaf":false,"id":745,"left":{"leaf":false,"id":730,"left":{"leaf":false,"id":568,"left":{"leaf":true,"id":396,"label":"396","site_id":396},"right":{"leaf":true,"id":100,"label":"100","site_id":100}},"right":{"leaf":false,"id":721,"left":{"leaf":false,"id":435,"left":{"leaf":true,"id":194,"label":"194","site_id":194},"right":{"leaf":true,"id":298,"label":"298","site_id":298}},"right":{"leaf":true,"id":170,"label":"170","site_id":170}}},"right":{"leaf":false,"id":617,"left":{"leaf":false,"id":550,"left":{"leaf":true,"id":377,"label":"377","site_id":377},"right":{"leaf":true,"id":217,"label":"217","site_id":217}},"right":{"leaf":true,"id":291,"label":"291","site_id":291}}},"right":{"leaf":false,"id":680,"left":{"leaf":false,"id":653,"left":{"leaf":false,"id":497,"left":{"leaf":false,"id":429,"left":{"leaf":true,"id":364,"label":"364","site_id":364},"right":{"leaf":true,"id":328,"label":"328","site_id":328}},"right":{"leaf":true,"id":53,"label":"53","site_id":53}},"right":{"leaf":false,"id":635,"left":{"leaf":true,"id":353,"label":"353","site_id":353},"right":{"leaf":false,"id":513,"left":{"leaf":true,"id":199,"label":"199","site_id":199},"right":{"leaf":false,"id":445,"left":{"leaf":true,"id":369,"label":"369","site_id":369},"right":{"leaf":true,"id":313,"label":"313","site_id":313}}}}},"right":{"leaf":true,"id":210,"label":"210","site_id":210}}},"right":{"leaf":false,"id":646,"left":{"leaf":false,"id":603,"left":{"leaf":true,"id":79,"label":"79","site_id":79},"right":{"leaf":false,"id":502,"left":{"leaf":false,"id":477,"left":{"leaf":false,"id":461,"left":{"leaf":true,"id":125,"label":"125","site_id":125},"right":{"leaf":true,"id":40,"label":"40","site_id":40}},"right":{"leaf":true,"id":128,"label":"128","site_id":128}},"right":{"leaf":true,"id":34,"label":"34","site_id":34}}},"right":{"leaf":false,"id":546,"left":{"leaf":false,"id":515,"left":{"leaf":false,"id":504,"left":{"leaf":true,"id":204,"label":"204","site_id":204},"right":{"leaf":true,"id":191,"label":"191","site_id":191}},"right":{"leaf":true,"id":322,"label":"322","site_id":322}},"right":{"leaf":true,"id":312,"label":"312","site_id":312}}}},"right":{"leaf":false,"id":596,"left":{"leaf":true,"id":112,"label":"112","site_id":112},"right":{"leaf":false,"id":581,"left":{"leaf":true,"id":131,"label":"131","site_id":131},"right":{"leaf":true,"id":122,"label":"122","site_id":122}}}},"right":{"leaf":false,"id":664,"left":{"leaf":false,"id":576,"left":{"leaf":true,"id":257,"label":"257","site_id":257},"right":{"leaf":true,"id":0,"label":"0","site_id":0}},"right":{"leaf":false,"id":658,"left":{"leaf":true,"id":130,"label":"130","site_id":130},"right":{"leaf":false,"id":628,"left":{"leaf":false,"id":432,"left":{"leaf":false,"id":417,"left":{"leaf":true,"id":93,"label":"93","site_id":93},"right":{"leaf":true,"id":69,"label":"69","site_id":69}},"right":{"leaf":true,"id":293,"label":"293","site_id":293}},"right":{"leaf":false,"id":575,"left":{"leaf":true,"id":16,"label":"16","site_id":16},"right":{"leaf":false,"id":409,"left":{"leaf":true,"id":303,"label":"303","site_id":303},"right":{"leaf":true,"id":33,"label":"33","site_id":33}}}}}}}}},"right":{"leaf":false,"id":468,"left":{"leaf":true,"id":342,"label":"342","site_id":342},"right":{"leaf":true,"id":351,"label":"351","site_id":351}}},"right":{"leaf":false,"id":684,"left":{"leaf":true,"id":238,"label":"238","site_id":238},"right":{"leaf":false,"id":667,"left":{"leaf":false,"id":408,"left":{"leaf":true,"id":94,"label":"94","site_id":94},"right":{"leaf":true,"id":177,"label":"177","site_id":177}},"right":{"leaf":true,"id":350,"label":"350","site_id":350}}}},"right":{"leaf":false,"id":795,"left":{"leaf":false,"id":789,"left":{"leaf":false,"id":782,"left":{"leaf":false,"id":754,"left":{"leaf":false,"id":659,"left":{"leaf":false,"id":621,"left":{"leaf":true,"id":47,"label":"47","site_id":47},"right":{"leaf":true,"id":233,"label":"233","site_id":233}},"right":{"leaf":true,"id":18,"label":"18","site_id":18}},"right":{"leaf":false,"id":692,"left":{"leaf":true,"id":314,"label":"314","site_id":314},"right":{"leaf":false,"id":682,"left":{"leaf":false,"id":650,"left":{"leaf":true,"id":30,"label":"30","site_id":30},"right":{"leaf":false,"id":612,"left":{"leaf":true,"id":74,"label":"74","site_id":74},"right":{"leaf":true,"id":372,"label":"372","site_id":372}}},"right":{"leaf":false,"id":656,"left":{"leaf":true,"id":15,"label":"15","site_id":15},"right":{"leaf":false,"id":535,"left":{"leaf":true,"id":296,"label":"296","site_id":296},"right":{"leaf":true,"id":25,"label":"25","site_id":25}}}}}},"right":{"leaf":false,"id":779,"left":{"leaf":false,"id":766,"left":{"leaf":false,"id":753,"left":{"leaf":false,"id":752,"left":{"leaf":false,"id":751,"left":{"leaf":false,"id":741,"left":{"leaf":false,"id":678,"left":{"leaf":false,"id":560,"left":{"leaf":true,"id":273,"label":"273","site_id":273},"right":{"leaf":true,"id":244,"label":"244","site_id":244}},"right":{"leaf":false,"id":672,"left":{"leaf":false,"id":548,"left":{"leaf":true,"id":205,"label":"205","site_id":205},"right":{"leaf":false,"id":426,"left":{"leaf":true,"id":305,"label":"305","site_id":305},"right":{"leaf":true,"id":59,"label":"59","site_id":59}}},"right":{"leaf":false,"id":644,"left":{"leaf":true,"id":297,"label":"297","site_id":297},"right":{"leaf":true,"id":116,"label":"116","site_id":116}}}},"right":{"leaf":false,"id":641,"left":{"leaf":true,"id":348,"label":"348","site_id":348},"right":{"leaf":true,"id":174,"label":"174","site_id":174}}},"right":{"leaf":false,"id":591,"left":{"leaf":true,"id":295,"label":"295","site_id":295},"right":{"leaf":true,"id":37,"label":"37","site_id":37}}},"right":{"leaf":false,"id":495,"left":{"leaf":true,"id":202,"label":"202","site_id":202},"right":{"leaf":true,"id":361,"label":"361","site_id":361}}},"right":{"leaf":false,"id":710,"left":{"leaf":false,"id":679,"left":{"leaf":false,"id":559,"left":{"leaf":false,"id":413,"left":{"leaf":true,"id":334,"label":"334","site_id":334},"right":{"leaf":true,"id":380,"label":"380","site_id":380}},"right":{"leaf":false,"id":510,"left":{"leaf":true,"id":207,"label":"207","site_id":207},"right":{"leaf":true,"id":46,"label":"46","site_id":46}}},"right":{"leaf":false,"id":660,"left":{"leaf":false,"id":554,"left":{"leaf":true,"id":182,"label":"182","site_id":182},"right":{"leaf":false,"id":523,"left":{"leaf":false,"id":517,"left":{"leaf":false,"id":425,"left":{"leaf":true,"id":268,"label":"268","site_id":268},"right":{"leaf":true,"id":4,"label":"4","site_id":4}},"right":{"leaf":false,"id":484,"left":{"leaf":true,"id":190,"label":"190","site_id":190},"right":{"leaf":false,"id":404,"left":{"leaf":true,"id":38,"label":"38","site_id":38},"right":{"leaf":true,"id":349,"label":"349","site_id":349}}}},"right":{"leaf":true,"id":394,"label":"394","site_id":394}}},"right":{"leaf":false,"id":582,"left":{"leaf":true,"id":144,"label":"144","site_id":144},"right":{"leaf":false,"id":503,"left":{"leaf":true,"id":14,"label":"14","site_id":14},"right":{"leaf":true,"id":375,"label":"375","site_id":375}}}}},"right":{"leaf":false,"id":683,"left":{"leaf":true,"id":22,"label":"22","site_id":22},"right":{"leaf":true,"id":188,"label":"188","site_id":188}}}},"right":{"leaf":false,"id":764,"left":{"leaf":false,"id":722,"left":{"leaf":false,"id":712,"left":{"leaf":false,"id":666,"left":{"leaf":false,"id":505,"left":{"leaf":false,"id":458,"left":{"leaf":true,"id":275,"label":"275","site_id":275},"right":{"leaf":true,"id":253,"label":"253","site_id":253}},"right":{"leaf":true,"id":160,"label":"160","site_id":160}},"right":{"leaf":false,"id":531,"left":{"leaf":true,"id":187,"label":"187","site_id":187},"right":{"leaf":false,"id":414,"left":{"leaf":true,"id":31,"label":"31","site_id":31},"right":{"leaf":true,"id":230,"label":"230","site_id":230}}}},"right":{"leaf":false,"id":454,"left":{"leaf":true,"id":306,"label":"306","site_id":306},"right":{"leaf":false,"id":415,"left":{"leaf":true,"id":311,"label":"311","site_id":311},"right":{"leaf":true,"id":108,"label":"108","site_id":108}}}},"right":{"leaf":false,"id":662,"left":{"leaf":false,"id":636,"left":{"leaf":false,"id":630,"left":{"leaf":true,"id":8,"label":"8","site_id":8},"right":{"leaf":false,"id":556,"left":{"leaf":false,"id":437,"left":{"leaf":false,"id":434,"left":{"leaf":true,"id":81,"label":"81","site_id":81},"right":{"leaf":true,"id":283,"label":"283","site_id":283}},"right":{"leaf":true,"id":235,"label":"235","site_id":235}},"right":{"leaf":true,"id":96,"label":"96","site_id":96}}},"right":{"leaf":false,"id":411,"left":{"leaf":true,"id":77,"label":"77","site_id":77},"right":{"leaf":true,"id":161,"label":"161","site_id":161}}},"right":{"leaf":false,"id":532,"left":{"leaf":true,"id":62,"label":"62","site_id":62},"right":{"leaf":true,"id":214,"label":"214","site_id":214}}}},"right":{"leaf":false,"id":757,"left":{"leaf":false,"id":746,"left":{"leaf":false,"id":562,"left":{"leaf":false,"id":509,"left":{"leaf":true,"id":266,"label":"266","site_id":266},"right":{"leaf":true,"id":285,"label":"285","site_id":285}},"right":{"leaf":false,"id":549,"left":{"leaf":true,"id":165,"label":"165","site_id":165},"right":{"leaf":true,"id":179,"label":"179","site_id":179}}},"right":{"leaf":false,"id":553,"left":{"leaf":false,"id":496,"left":{"leaf":true,"id":175,"label":"175","site_id":175},"right":{"leaf":true,"id":335,"label":"335","site_id":335}},"right":{"leaf":true,"id":192,"label":"192","site_id":192}}},"right":{"leaf":false,"id":691,"left":{"leaf":false,"id":577,"left":{"leaf":true,"id":50,"label":"50","site_id":50},"right":{"leaf":true,"id":157,"label":"157","site_id":157}},"right":{"leaf":true,"id":111,"label":"111","site_id":111}}}}},"right":{"leaf":false,"id":758,"left":{"leaf":false,"id":743,"left":{"leaf":false,"id":485,"left":{"leaf":true,"id":26,"label":"26","site_id":26},"right":{"leaf":false,"id":421,"left":{"leaf":true,"id":243,"label":"243","site_id":243},"right":{"leaf":true,"id":23,"label":"23","site_id":23}}},"right":{"leaf":false,"id":720,"left":{"leaf":true,"id":49,"label":"49","site_id":49},"right":{"leaf":false,"id":697,"left":{"leaf":false,"id":631,"left":{"leaf":true,"id":35,"label":"35","site_id":35},"right":{"leaf":true,"id":147,"label":"147","site_id":147}},"right":{"leaf":false,"id":622,"left":{"leaf":false,"id":555,"left":{"leaf":false,"id":486,"left":{"leaf":true,"id":86,"label":"86","site_id":86},"right":{"leaf":true,"id":325,"label":"325","site_id":325}},"right":{"leaf":true,"id":65,"label":"65","site_id":65}},"right":{"leaf":true,"id":78,"label":"78","site_id":78}}}}},"right":{"leaf":false,"id":593,"left":{"leaf":true,"id":107,"label":"107","site_id":107},"right":{"leaf":true,"id":333,"label":"333","site_id":333}}}}},"right":{"leaf":false,"id":788,"left":{"leaf":false,"id":652,"left":{"leaf":false,"id":525,"left":{"leaf":true,"id":124,"label":"124","site_id":124},"right":{"leaf":true,"id":119,"label":"119","site_id":119}},"right":{"leaf":false,"id":645,"left":{"leaf":false,"id":424,"left":{"leaf":true,"id":344,"label":"344","site_id":344},"right":{"leaf":true,"id":310,"label":"310","site_id":310}},"right":{"leaf":true,"id":332,"label":"332","site_id":332}}},"right":{"leaf":false,"id":740,"left":{"leaf":false,"id":737,"left":{"leaf":false,"id":649,"left":{"leaf":true,"id":150,"label":"150","site_id":150},"right":{"leaf":false,"id":609,"left":{"leaf":true,"id":189,"label":"189","site_id":189},"right":{"leaf":false,"id":494,"left":{"leaf":true,"id":183,"label":"183","site_id":183},"right":{"leaf":true,"id":173,"label":"173","site_id":173}}}},"right":{"leaf":false,"id":620,"left":{"leaf":true,"id":299,"label":"299","site_id":299},"right":{"leaf":false,"id":574,"left":{"leaf":false,"id":512,"left":{"leaf":true,"id":32,"label":"32","site_id":32},"right":{"leaf":false,"id":460,"left":{"leaf":true,"id":10,"label":"10","site_id":10},"right":{"leaf":true,"id":105,"label":"105","site_id":105}}},"right":{"leaf":false,"id":442,"left":{"leaf":true,"id":251,"label":"251","site_id":251},"right":{"leaf":true,"id":395,"label":"395","site_id":395}}}}},"right":{"leaf":false,"id":669,"left":{"leaf":false,"id":534,"left":{"leaf":true,"id":279,"label":"279","site_id":279},"right":{"leaf":true,"id":145,"label":"145","site_id":145}},"right":{"leaf":true,"id":319,"label":"319","site_id":319}}}}},"right":{"leaf":false,"id":794,"left":{"leaf":false,"id":784,"left":{"leaf":false,"id":773,"left":{"leaf":false,"id":771,"left":{"leaf":true,"id":95,"label":"95","site_id":95},"right":{"leaf":false,"id":769,"left":{"leaf":false,"id":689,"left":{"leaf":false,"id":657,"left":{"leaf":true,"id":115,"label":"115","site_id":115},"right":{"leaf":true,"id":267,"label":"267","site_id":267}},"right":{"leaf":false,"id":638,"left":{"leaf":true,"id":287,"label":"287","site_id":287},"right":{"leaf":true,"id":87,"label":"87","site_id":87}}},"right":{"leaf":false,"id":703,"left":{"leaf":false,"id":643,"left":{"leaf":false,"id":563,"left":{"leaf":false,"id":533,"left":{"leaf":true,"id":368,"label":"368","site_id":368},"right":{"leaf":false,"id":457,"left":{"leaf":true,"id":261,"label":"261","site_id":261},"right":{"leaf":true,"id":231,"label":"231","site_id":231}}},"right":{"leaf":true,"id":41,"label":"41","site_id":41}},"right":{"leaf":false,"id":626,"left":{"leaf":false,"id":520,"left":{"leaf":false,"id":467,"left":{"leaf":true,"id":357,"label":"357","site_id":357},"right":{"leaf":true,"id":140,"label":"140","site_id":140}},"right":{"leaf":true,"id":236,"label":"236","site_id":236}},"right":{"leaf":false,"id":491,"left":{"leaf":true,"id":168,"label":"168","site_id":168},"right":{"leaf":true,"id":358,"label":"358","site_id":358}}}},"right":{"leaf":false,"id":639,"left":{"leaf":true,"id":222,"label":"222","site_id":222},"right":{"leaf":true,"id":301,"label":"301","site_id":301}}}}},"right":{"leaf":false,"id":726,"left":{"leaf":false,"id":698,"left":{"leaf":false,"id":687,"left":{"leaf":false,"id":610,"left":{"leaf":true,"id":378,"label":"378","site_id":378},"right":{"leaf":false,"id":542,"left":{"leaf":true,"id":169,"label":"169","site_id":169},"right":{"leaf":false,"id":453,"left":{"leaf":true,"id":389,"label":"389","site_id":389},"right":{"leaf":true,"id":307,"label":"307","site_id":307}}}},"right":{"leaf":true,"id":9,"label":"9","site_id":9}},"right":{"leaf":true,"id":42,"label":"42","site_id":42}},"right":{"leaf":false,"id":589,"left":{"leaf":false,"id":526,"left":{"leaf":false,"id":451,"left":{"leaf":true,"id":196,"label":"196","site_id":196},"right":{"leaf":true,"id":208,"label":"208","site_id":208}},"right":{"leaf":true,"id":255,"label":"255","site_id":255}},"right":{"leaf":true,"id":360,"label":"360","site_id":360}}}},"right":{"leaf":false,"id":696,"left":{"leaf":false,"id":633,"left":{"leaf":true,"id":61,"label":"61","site_id":61},"right":{"leaf":false,"id":489,"left":{"leaf":true,"id":104,"label":"104","site_id":104},"right":{"leaf":false,"id":406,"left":{"leaf":true,"id":246,"label":"246","site_id":246},"right":{"leaf":true,"id":365,"label":"365","site_id":365}}}},"right":{"leaf":true,"id":248,"label":"248","site_id":248}}},"right":{"leaf":false,"id":791,"left":{"leaf":false,"id":748,"left":{"leaf":false,"id":629,"left":{"leaf":false,"id":498,"left":{"leaf":true,"id":109,"label":"109","site_id":109},"right":{"leaf":true,"id":101,"label":"101","site_id":101}},"right":{"leaf":false,"id":578,"left":{"leaf":true,"id":70,"label":"70","site_id":70},"right":{"leaf":true,"id":85,"label":"85","site_id":85}}},"right":{"leaf":true,"id":152,"label":"152","site_id":152}},"right":{"leaf":false,"id":790,"left":{"leaf":false,"id":777,"left":{"leaf":false,"id":774,"left":{"leaf":false,"id":750,"left":{"leaf":true,"id":329,"label":"329","site_id":329},"right":{"leaf":false,"id":685,"left":{"leaf":false,"id":561,"left":{"leaf":false,"id":544,"left":{"leaf":true,"id":149,"label":"149","site_id":149},"right":{"leaf":true,"id":373,"label":"373","site_id":373}},"right":{"leaf":true,"id":129,"label":"129","site_id":129}},"right":{"leaf":false,"id":541,"left":{"leaf":true,"id":193,"label":"193","site_id":193},"right":{"leaf":true,"id":398,"label":"398","site_id":398}}}},"right":{"leaf":false,"id":607,"left":{"leaf":true,"id":237,"label":"237","site_id":237},"right":{"leaf":true,"id":242,"label":"242","site_id":242}}},"right":{"leaf":false,"id":693,"left":{"leaf":false,"id":624,"left":{"leaf":true,"id":384,"label":"384","site_id":384},"right":{"leaf":false,"id":519,"left":{"leaf":true,"id":28,"label":"28","site_id":28},"right":{"leaf":true,"id":118,"label":"118","site_id":118}}},"right":{"leaf":false,"id":480,"left":{"leaf":true,"id":72,"label":"72","site_id":72},"right":{"leaf":false,"id":412,"left":{"leaf":true,"id":200,"label":"200","site_id":200},"right":{"leaf":true,"id":52,"label":"52","site_id":52}}}}},"right":{"leaf":false,"id":775,"left":{"leaf":false,"id":729,"left":{"leaf":false,"id":521,"left":{"leaf":true,"id":67,"label":"67","site_id":67},"right":{"leaf":true,"id":185,"label":"185","site_id":185}},"right":{"leaf":false,"id":579,"left":{"leaf":true,"id":195,"label":"195","site_id":195},"right":{"leaf":true,"id":166,"label":"166","site_id":166}}},"right":{"leaf":false,"id":586,"left":{"leaf":false,"id":565,"left":{"leaf":false,"id":492,"left":{"leaf":true,"id":366,"label":"366","site_id":366},"right":{"leaf":true,"id":270,"label":"270","site_id":270}},"right":{"leaf":true,"id":17,"label":"17","site_id":17}},"right":{"leaf":true,"id":209,"label":"209","site_id":209}}}}}}}},"right":{"leaf":false,"id":793,"left":{"leaf":false,"id":772,"left":{"leaf":false,"id":763,"left":{"leaf":false,"id":708,"left":{"leaf":false,"id":655,"left":{"leaf":false,"id":488,"left":{"leaf":false,"id":469,"left":{"leaf":true,"id":354,"label":"354","site_id":354},"right":{"leaf":true,"id":103,"label":"103","site_id":103}},"right":{"leaf":true,"id":66,"label":"66","site_id":66}},"right":{"leaf":false,"id":619,"left":{"leaf":true,"id":387,"label":"387","site_id":387},"right":{"leaf":false,"id":602,"left":{"leaf":true,"id":309,"label":"309","site_id":309},"right":{"leaf":false,"id":598,"left":{"leaf":false,"id":588,"left":{"leaf":false,"id":571,"left":{"leaf":true,"id":232,"label":"232","site_id":232},"right":{"leaf":true,"id":359,"label":"359","site_id":359}},"right":{"leaf":false,"id":473,"left":{"leaf":true,"id":29,"label":"29","site_id":29},"right":{"leaf":true,"id":80,"label":"80","site_id":80}}},"right":{"leaf":true,"id":97,"label":"97","site_id":97}}}}},"right":{"leaf":false,"id":706,"left":{"leaf":false,"id":654,"left":{"leaf":true,"id":27,"label":"27","site_id":27},"right":{"leaf":false,"id":439,"left":{"leaf":true,"id":330,"label":"330","site_id":330},"right":{"leaf":true,"id":308,"label":"308","site_id":308}}},"right":{"leaf":false,"id":637,"left":{"leaf":true,"id":89,"label":"89","site_id":89},"right":{"leaf":false,"id":611,"left":{"leaf":false,"id":572,"left":{"leaf":true,"id":272,"label":"272","site_id":272},"right":{"leaf":true,"id":390,"label":"390","site_id":390}},"right":{"leaf":true,"id":323,"label":"323","site_id":323}}}}},"right":{"leaf":false,"id":673,"left":{"leaf":true,"id":172,"label":"172","site_id":172},"right":{"leaf":false,"id":540,"left":{"leaf":true,"id":376,"label":"376","site_id":376},"right":{"leaf":false,"id":427,"left":{"leaf":true,"id":321,"label":"321","site_id":321},"right":{"leaf":true,"id":184,"label":"184","site_id":184}}}}},"right":{"leaf":false,"id":768,"left":{"leaf":false,"id":742,"left":{"leaf":false,"id":728,"left":{"leaf":false,"id":514,"left":{"leaf":true,"id":260,"label":"260","site_id":260},"right":{"leaf":true,"id":269,"label":"269","site_id":269}},"right":{"leaf":true,"id":370,"label":"370","site_id":370}},"right":{"leaf":false,"id":694,"left":{"leaf":false,"id":566,"left":{"leaf":false,"id":508,"left":{"leaf":true,"id":300,"label":"300","site_id":300},"right":{"leaf":true,"id":218,"label":"218","site_id":218}},"right":{"leaf":false,"id":446,"left":{"leaf":true,"id":203,"label":"203","site_id":203},"right":{"leaf":true,"id":347,"label":"347","site_id":347}}},"right":{"leaf":true,"id":163,"label":"163","site_id":163}}},"right":{"leaf":false,"id":739,"left":{"leaf":false,"id":647,"left":{"leaf":false,"id":640,"left":{"leaf":true,"id":254,"label":"254","site_id":254},"right":{"leaf":true,"id":216,"label":"216","site_id":216}},"right":{"leaf":false,"id":627,"left":{"leaf":false,"id":511,"left":{"leaf":false,"id":462,"left":{"leaf":true,"id":114,"label":"114","site_id":114},"right":{"leaf":true,"id":213,"label":"213","site_id":213}},"right":{"leaf":true,"id":281,"label":"281","site_id":281}},"right":{"leaf":false,"id":441,"left":{"leaf":true,"id":20,"label":"20","site_id":20},"right":{"leaf":true,"id":120,"label":"120","site_id":120}}}},"right":{"leaf":false,"id":733,"left":{"leaf":false,"id":695,"left":{"leaf":false,"id":618,"left":{"leaf":false,"id":524,"left":{"leaf":true,"id":55,"label":"55","site_id":55},"right":{"leaf":true,"id":385,"label":"385","site_id":385}},"right":{"leaf":false,"id":590,"left":{"leaf":true,"id":234,"label":"234","site_id":234},"right":{"leaf":true,"id":156,"label":"156","site_id":156}}},"right":{"leaf":false,"id":529,"left":{"leaf":true,"id":148,"label":"148","site_id":148},"right":{"leaf":true,"id":36,"label":"36","site_id":36}}},"right":{"leaf":true,"id":211,"label":"211","site_id":211}}}}},"right":{"leaf":false,"id":792,"left":{"leaf":false,"id":767,"left":{"leaf":false,"id":717,"left":{"leaf":false,"id":623,"left":{"leaf":false,"id":450,"left":{"leaf":true,"id":282,"label":"282","site_id":282},"right":{"leaf":true,"id":241,"label":"241","site_id":241}},"right":{"leaf":false,"id":585,"left":{"leaf":false,"id":527,"left":{"leaf":true,"id":73,"label":"73","site_id":73},"right":{"leaf":false,"id":466,"left":{"leaf":true,"id":141,"label":"141","site_id":141},"right":{"leaf":true,"id":60,"label":"60","site_id":60}}},"right":{"leaf":true,"id":186,"label":"186","site_id":186}}},"right":{"leaf":false,"id":714,"left":{"leaf":false,"id":674,"left":{"leaf":true,"id":3,"label":"3","site_id":3},"right":{"leaf":false,"id":625,"left":{"leaf":false,"id":613,"left":{"leaf":true,"id":355,"label":"355","site_id":355},"right":{"leaf":true,"id":259,"label":"259","site_id":259}},"right":{"leaf":false,"id":433,"left":{"leaf":true,"id":153,"label":"153","site_id":153},"right":{"leaf":true,"id":315,"label":"315","site_id":315}}}},"right":{"leaf":false,"id":704,"left":{"leaf":false,"id":699,"left":{"leaf":false,"id":587,"left":{"leaf":false,"id":567,"left":{"leaf":true,"id":249,"label":"249","site_id":249},"right":{"leaf":true,"id":102,"label":"102","site_id":102}},"right":{"leaf":true,"id":341,"label":"341","site_id":341}},"right":{"leaf":true,"id":252,"label":"252","site_id":252}},"right":{"leaf":false,"id":569,"left":{"leaf":false,"id":405,"left":{"leaf":true,"id":64,"label":"64","site_id":64},"right":{"leaf":false,"id":400,"left":{"leaf":true,"id":362,"label":"362","site_id":362},"right":{"leaf":true,"id":19,"label":"19","site_id":19}}},"right":{"leaf":true,"id":239,"label":"239","site_id":239}}}}},"right":{"leaf":false,"id":725,"left":{"leaf":false,"id":716,"left":{"leaf":true,"id":288,"label":"288","site_id":288},"right":{"leaf":false,"id":675,"left":{"leaf":false,"id":670,"left":{"leaf":false,"id":614,"left":{"leaf":true,"id":176,"label":"176","site_id":176},"right":{"leaf":true,"id":343,"label":"343","site_id":343}},"right":{"leaf":false,"id":481,"left":{"leaf":true,"id":229,"label":"229","site_id":229},"right":{"leaf":true,"id":167,"label":"167","site_id":167}}},"right":{"leaf":true,"id":224,"label":"224","site_id":224}}},"right":{"leaf":false,"id":592,"left":{"leaf":false,"id":507,"left":{"leaf":true,"id":271,"label":"271","site_id":271},"right":{"leaf":true,"id":58,"label":"58","site_id":58}},"right":{"leaf":false,"id":444,"left":{"leaf":true,"id":110,"label":"110","site_id":110},"right":{"leaf":true,"id":317,"label":"317","site_id":317}}}}},"right":{"leaf":false,"id":785,"left":{"leaf":false,"id":770,"left":{"leaf":false,"id":761,"left":{"leaf":false,"id":747,"left":{"leaf":true,"id":327,"label":"327","site_id":327},"right":{"leaf":false,"id":688,"left":{"leaf":false,"id":522,"left":{"leaf":true,"id":212,"label":"212","site_id":212},"right":{"leaf":true,"id":274,"label":"274","site_id":274}},"right":{"leaf":false,"id":668,"left":{"leaf":false,"id":665,"left":{"leaf":false,"id":518,"left":{"leaf":true,"id":133,"label":"133","site_id":133},"right":{"leaf":true,"id":43,"label":"43","site_id":43}},"right":{"leaf":true,"id":263,"label":"263","site_id":263}},"right":{"leaf":false,"id":476,"left":{"leaf":true,"id":258,"label":"258","site_id":258},"right":{"leaf":true,"id":392,"label":"392","site_id":392}}}}},"right":{"leaf":false,"id":749,"left":{"leaf":false,"id":557,"left":{"leaf":false,"id":419,"left":{"leaf":true,"id":346,"label":"346","site_id":346},"right":{"leaf":true,"id":137,"label":"137","site_id":137}},"right":{"leaf":true,"id":138,"label":"138","site_id":138}},"right":{"leaf":true,"id":215,"label":"215","site_id":215}}},"right":{"leaf":true,"id":197,"label":"197","site_id":197}},"right":{"leaf":false,"id":744,"left":{"leaf":false,"id":719,"left":{"leaf":false,"id":551,"left":{"leaf":true,"id":206,"label":"206","site_id":206},"right":{"leaf":false,"id":543,"left":{"leaf":true,"id":88,"label":"88","site_id":88},"right":{"leaf":false,"id":530,"left":{"leaf":false,"id":472,"left":{"leaf":true,"id":164,"label":"164","site_id":164},"right":{"leaf":true,"id":121,"label":"121","site_id":121}},"right":{"leaf":true,"id":54,"label":"54","site_id":54}}}},"right":{"leaf":true,"id":99,"label":"99","site_id":99}},"right":{"leaf":false,"id":671,"left":{"leaf":false,"id":634,"left":{"leaf":true,"id":98,"label":"98","site_id":98},"right":{"leaf":false,"id":470,"left":{"leaf":true,"id":337,"label":"337","site_id":337},"right":{"leaf":true,"id":11,"label":"11","site_id":11}}},"right":{"leaf":false,"id":661,"left":{"leaf":false,"id":597,"left":{"leaf":true,"id":397,"label":"397","site_id":397},"right":{"leaf":true,"id":356,"label":"356","site_id":356}},"right":{"leaf":false,"id":545,"left":{"leaf":true,"id":106,"label":"106","site_id":106},"right":{"leaf":true,"id":13,"label":"13","site_id":13}}}}}}}}},"num_sites":400,"sites":[{"x":254.58918851131662,"y":98.81524219952921,"cluster":1},{"x":133.2981435789426,"y":289.7067154028398,"cluster":1},{"x":360.86428240073263,"y":108.76541509157903,"cluster":1},{"x":90.36659973205198,"y":403.22070113756814,"cluster":1},{"x":439.0847472939032,"y":135.51869768029502,"cluster":1},{"x":375.7186497648851,"y":90.15933155396418,"cluster":1},{"x":80.64788063304101,"y":286.276307891649,"cluster":1},{"x":183.34663224197695,"y":169.53502372235366,"cluster":1},{"x":303.2614502480645,"y":118.87869509214491,"cluster":1},{"x":145.4129505277182,"y":442.51671094512096,"cluster":1},{"x":227.6237155371008,"y":262.3230470360061,"cluster":1},{"x":456.8070481706146,"y":405.0300281471128,"cluster":1},{"x":364.16174944757677,"y":104.82825087783075,"cluster":1},{"x":419.67453333970724,"y":382.3121001351003,"cluster":1},{"x":447.0821096690901,"y":191.27020133426632,"cluster":1},{"x":353.7203819880749,"y":281.2683920454091,"cluster":1},{"x":202.5991793169286,"y":125.99947931968318,"cluster":1},{"x":258.98054107455,"y":405.1993470979426,"cluster":1},{"x":404.88021846682835,"y":304.80599265501263,"cluster":1},{"x":130.71144653199613,"y":352.74805137684666,"cluster":1},{"x":390.98258308301405,"y":475.10891341847656,"cluster":1},{"x":49.06449821970721,"y":298.7657933839164,"cluster":1},{"x":360.8575658510792,"y":204.32771691960687,"cluster":1},{"x":493.2926629866971,"y":65.20046891633395,"cluster":1},{"x":448.35614468622623,"y":6.82939573137651,"cluster":1},{"x":319.37879552917417,"y":195.08360881579887,"cluster":1},{"x":486.0964370095946,"y":47.84880499505655,"cluster":1},{"x":415.18065766094116,"y":384.2250666488775,"cluster":1},{"x":279.0382911023461,"y":490.34368136790596,"cluster":1},{"x":388.454785184517,"y":457.31982826045294,"cluster":1},{"x":466.65989370137544,"y":271.8728038968669,"cluster":1},{"x":442.45181901299804,"y":247.82999719854752,"cluster":1},{"x":225.74209405590335,"y":269.2750975590748,"cluster":1},{"x":215.1682439170711,"y":122.22538897477685,"cluster":1},{"x":64.94031284782842,"y":99.17961251345291,"cluster":1},{"x":481.79460669700234,"y":72.94955000789997,"cluster":1},{"x":470.5600987920094,"y":450.19062833234557,"cluster":1},{"x":493.41803760717784,"y":218.82357277119806,"cluster":1},{"x":438.25117293401354,"y":187.96918918642658,"cluster":1},{"x":120.61656951692208,"y":272.50858630945567,"cluster":1},{"x":143.69629422628654,"y":153.3716833686289,"cluster":1},{"x":136.2258672562003,"y":480.11801421738943,"cluster":1},{"x":162.79492591004632,"y":460.3082174842887,"cluster":1},{"x":189.26367483229183,"y":294.10434684057986,"cluster":1},{"x":110.32813358794903,"y":312.0478639181468,"cluster":1},{"x":379.764785142017,"y":1.1407421919936707,"cluster":1},{"x":453.63986834569556,"y":208.3248399025563,"cluster":1},{"x":416.1100139033074,"y":329.875748064178,"cluster":1},{"x":84.48132358604941,"y":272.78909987341854,"cluster":1},{"x":460.3243573433449,"y":71.16050877076378,"cluster":1},{"x":331.83858609061247,"y":231.09694211746418,"cluster":1},{"x":102.77543748437763,"y":3.6307446010668816,"cluster":1},{"x":265.30032460744746,"y":458.2513781164794,"cluster":1},{"x":319.7203061487681,"y":62.37163158961014,"cluster":1},{"x":462.3211199477462,"y":405.6792273898931,"cluster":1},{"x":405.2291082355604,"y":417.80184766371167,"cluster":1},{"x":385.5972094791217,"y":75.97140284508517,"cluster":1},{"x":23.156460300763563,"y":289.88380773036613,"cluster":1},{"x":148.69531901109798,"y":164.21432999214662,"cluster":1},{"x":457.0367357531562,"y":131.3002621751263,"cluster":1},{"x":143.0617676475437,"y":395.4056269079714,"cluster":1},{"x":140.0467018854242,"y":484.33314382770754,"cluster":1},{"x":481.5874067325269,"y":11.57343358796669,"cluster":1},{"x":113.50930640060025,"y":165.83885480546869,"cluster":1},{"x":129.01581769081238,"y":335.9087239955136,"cluster":1},{"x":490.804882523348,"y":72.93466379241309,"cluster":1},{"x":367.6556011180621,"y":350.47157294101635,"cluster":1},{"x":308.01106260975615,"y":394.7943302711775,"cluster":1},{"x":4.094225425408265,"y":116.84703347558504,"cluster":1},{"x":265.11040138278156,"y":115.29668355457879,"cluster":1},{"x":178.90939484446255,"y":479.5030069640478,"cluster":1},{"x":104.18465143503852,"y":171.17891346813315,"cluster":1},{"x":256.73569070377175,"y":459.5421850053574,"cluster":1},{"x":151.657324910758,"y":390.81739956092304,"cluster":1},{"x":496.46748882243276,"y":256.0418822982645,"cluster":1},{"x":110.35118589930079,"y":239.79177007851234,"cluster":1},{"x":60.8660784437516,"y":393.24019353354663,"cluster":1},{"x":271.8948632461604,"y":198.9837947298313,"cluster":1},{"x":479.3872039101963,"y":68.4536830363811,"cluster":1},{"x":134.8430313126288,"y":115.12068213577881,"cluster":1},{"x":307.6570119199366,"y":327.8014878406997,"cluster":1},{"x":284.76691624293915,"y":104.39349429824124,"cluster":1},{"x":15.697959871417734,"y":364.56254107371296,"cluster":1},{"x":1.5271751250412917,"y":171.06401453685504,"cluster":1},{"x":94.74257435531105,"y":248.30695173984333,"cluster":1},{"x":185.95867845570282,"y":488.81961218740196,"cluster":1},{"x":475.2719616642527,"y":115.81992125274449,"cluster":1},{"x":119.27689973450843,"y":383.0435372209758,"cluster":1},{"x":478.77704833542754,"y":441.2754744785935,"cluster":1},{"x":449.65793809774044,"y":367.1389865670923,"cluster":1},{"x":4.664611658123103,"y":195.11986338679458,"cluster":1},{"x":17.649709571018516,"y":237.57824660555417,"cluster":1},{"x":39.716290487465834,"y":334.6882861156703,"cluster":1},{"x":285.33896656396524,"y":48.44420515307751,"cluster":1},{"x":344.55764315982003,"y":340.70619514771926,"cluster":1},{"x":157.5291910638234,"y":464.8895617687144,"cluster":1},{"x":295.70578596843404,"y":122.51531839606724,"cluster":1},{"x":376.57685986257604,"y":392.15962968754496,"cluster":1},{"x":442.9377127584907,"y":415.1169238759959,"cluster":1},{"x":497.9886788944207,"y":402.6082653025598,"cluster":1},{"x":287.9580135983833,"y":8.938989340660488,"cluster":1},{"x":159.4000022141883,"y":497.4816828528987,"cluster":1},{"x":69.64326506204556,"y":358.61118048384753,"cluster":1},{"x":381.13459637224895,"y":361.1533528346485,"cluster":1},{"x":117.50198437382497,"y":497.97067062645283,"cluster":1},{"x":240.18866528818583,"y":270.96393729328696,"cluster":1},{"x":408.4125149358246,"y":333.0240830564849,"cluster":1},{"x":437.18710958113957,"y":59.853246480697436,"cluster":1},{"x":472.1878921595192,"y":306.65517289662273,"cluster":1},{"x":259.62729831298236,"y":497.5670436605054,"cluster":1},{"x":181.06533484333693,"y":186.4946818299439,"cluster":1},{"x":364.5561597841245,"y":263.379636406491,"cluster":1},{"x":246.8294387523042,"y":58.55856373241061,"cluster":1},{"x":63.71857818577993,"y":136.99399654436937,"cluster":1},{"x":424.95187384796645,"y":482.01241622721074,"cluster":1},{"x":10.17042097491478,"y":430.56422395294965,"cluster":1},{"x":459.8669093995323,"y":118.73459777017511,"cluster":1},{"x":215.36688241979974,"y":153.63097927560088,"cluster":1},{"x":293.300677323511,"y":485.2274125986248,"cluster":1},{"x":343.8171914078142,"y":252.16870842050633,"cluster":1},{"x":384.4336166216212,"y":477.865136772267,"cluster":1},{"x":494.5389831961642,"y":404.91408981069907,"cluster":1},{"x":236.59921185062186,"y":85.4698047521792,"cluster":1},{"x":48.7509552242271,"y":130.67842083036422,"cluster":1},{"x":322.20863629533005,"y":259.76977605843837,"cluster":1},{"x":139.50991847914844,"y":141.4423556543511,"cluster":1},{"x":163.6395086911711,"y":298.4235506248836,"cluster":1},{"x":9.32842635689984,"y":261.689675900378,"cluster":1},{"x":174.93859855244472,"y":28.980140445384464,"cluster":1},{"x":220.20170859835906,"y":346.65718048211886,"cluster":1},{"x":225.36180434489205,"y":111.39994573275723,"cluster":1},{"x":212.9278739066725,"y":92.96145704531355,"cluster":1},{"x":25.011357269977374,"y":239.5739362375166,"cluster":1},{"x":193.12270728904917,"y":292.40864897090495,"cluster":1},{"x":37.12891013226562,"y":6.65617688699611,"cluster":1},{"x":101.91059682871588,"y":61.701509349615826,"cluster":1},{"x":96.9643489416218,"y":246.96432259706984,"cluster":1},{"x":233.91565260576377,"y":233.2290959375617,"cluster":1},{"x":247.56431175083807,"y":212.70421699438813,"cluster":1},{"x":89.88229888797183,"y":165.15726609259426,"cluster":1},{"x":86.31046099618051,"y":436.8397370717026,"cluster":1},{"x":152.02186905511215,"y":374.63399896462215,"cluster":1},{"x":28.586504415206374,"y":284.05544524380235,"cluster":1},{"x":89.01223543116097,"y":4.08191010789438,"cluster":1},{"x":456.5642240630952,"y":189.94954937784584,"cluster":1},{"x":258.4697197563664,"y":319.270708214801,"cluster":1},{"x":121.7727092330338,"y":260.3461933163174,"cluster":1},{"x":481.66784954157396,"y":83.14586569354259,"cluster":1},{"x":461.8511445404063,"y":461.93088228936216,"cluster":1},{"x":220.29497146786107,"y":331.2352841054268,"cluster":1},{"x":284.68453208316805,"y":294.28961305198436,"cluster":1},{"x":138.1228470421822,"y":292.86401122326737,"cluster":1},{"x":226.98289920554583,"y":459.8718216038171,"cluster":1},{"x":27.600967216491128,"y":405.37772278993634,"cluster":1},{"x":25.288476893708406,"y":244.39913670818243,"cluster":1},{"x":150.5963945197819,"y":88.10898609355529,"cluster":1},{"x":397.3814568203604,"y":431.8064764787648,"cluster":1},{"x":351.76636212801236,"y":224.91588093187357,"cluster":1},{"x":183.10418996917284,"y":354.9288695867242,"cluster":1},{"x":166.3813341798698,"y":22.780856184420397,"cluster":1},{"x":465.734533087693,"y":299.83700450906485,"cluster":1},{"x":195.80823185649052,"y":227.17843537436144,"cluster":1},{"x":52.21309866853724,"y":285.9762047166168,"cluster":1},{"x":223.31919988547182,"y":440.70344839173094,"cluster":1},{"x":492.7656479823224,"y":426.07818528047557,"cluster":1},{"x":320.40842423266685,"y":137.79723742554694,"cluster":1},{"x":303.76034705602257,"y":355.1919808176883,"cluster":1},{"x":199.37982058833816,"y":219.3176963272435,"cluster":1},{"x":108.00123262786822,"y":467.11948238224903,"cluster":1},{"x":137.61091529452756,"y":422.1692155539207,"cluster":1},{"x":178.08289589780549,"y":13.04349920471003,"cluster":1},{"x":68.60335858234043,"y":81.24234113769045,"cluster":1},{"x":254.9178061463915,"y":365.2002926360374,"cluster":1},{"x":290.6980143471209,"y":275.50834576074396,"cluster":1},{"x":449.0964558720106,"y":152.07572456761403,"cluster":1},{"x":296.1626689679916,"y":173.27214773000378,"cluster":1},{"x":321.35193308992416,"y":178.79348949134746,"cluster":1},{"x":355.25317550452,"y":339.307832292317,"cluster":1},{"x":382.07419186255544,"y":39.115951893933335,"cluster":1},{"x":335.8035346371832,"y":162.884132479975,"cluster":1},{"x":352.55584459625976,"y":61.792488125431575,"cluster":1},{"x":144.91832343759097,"y":30.532925199593603,"cluster":1},{"x":436.4499154392642,"y":201.86721623400538,"cluster":1},{"x":289.420941446245,"y":266.8220703127197,"cluster":1},{"x":240.78146727174382,"y":330.9974178380512,"cluster":1},{"x":281.85340254540523,"y":410.36460274682526,"cluster":1},{"x":179.77871452598848,"y":315.83596132958246,"cluster":1},{"x":455.0289590175887,"y":256.82943216605696,"cluster":1},{"x":359.77575407456004,"y":192.0954697322678,"cluster":1},{"x":306.406016459675,"y":237.81448952090318,"cluster":1},{"x":425.48763717864523,"y":186.03892100253472,"cluster":1},{"x":87.88207645496495,"y":86.10136579136113,"cluster":1},{"x":269.0700278077504,"y":292.8308086210741,"cluster":1},{"x":194.9989895428931,"y":368.0313161612534,"cluster":1},{"x":305.54941928919,"y":90.43491855413444,"cluster":1},{"x":310.0058886372287,"y":426.5256742523724,"cluster":1},{"x":205.44623520585472,"y":452.55943253409595,"cluster":1},{"x":323.7436245298265,"y":405.61919138144634,"cluster":1},{"x":33.71198073872031,"y":362.5265863066672,"cluster":1},{"x":291.8948970366912,"y":37.283482994695675,"cluster":1},{"x":243.4629001425777,"y":475.884172113554,"cluster":1},{"x":19.786454579543733,"y":33.788033016656904,"cluster":1},{"x":319.41650542743935,"y":215.07748420412062,"cluster":1},{"x":356.6352057048904,"y":455.8795683984193,"cluster":1},{"x":99.42355892130861,"y":130.5652763503305,"cluster":1},{"x":444.8973640681312,"y":134.6564770031947,"cluster":1},{"x":473.0369818306279,"y":413.3899349867734,"cluster":1},{"x":383.20998397314395,"y":241.17285687751655,"cluster":1},{"x":187.67053667329313,"y":470.40171387271596,"cluster":1},{"x":250.30683557499873,"y":434.52759989307395,"cluster":1},{"x":355.57385996162157,"y":89.0887097902447,"cluster":1},{"x":436.2454653795483,"y":464.47738282153665,"cluster":1},{"x":180.5868070110019,"y":342.27872157763045,"cluster":1},{"x":454.3001565786487,"y":492.45760684233045,"cluster":1},{"x":494.4348980415676,"y":21.85618222534755,"cluster":1},{"x":215.95530613472965,"y":441.30399553029025,"cluster":1},{"x":412.18890156278195,"y":467.076733527283,"cluster":1},{"x":258.5764212329807,"y":18.938091534462824,"cluster":1},{"x":289.43571005177984,"y":439.0639326633517,"cluster":1},{"x":22.541150556182025,"y":170.81304778119863,"cluster":1},{"x":135.69342230648823,"y":218.63712914133617,"cluster":1},{"x":5.8800457179433,"y":114.01188269330726,"cluster":1},{"x":333.6530763372996,"y":431.7463873894967,"cluster":1},{"x":77.80714886532671,"y":178.54856767219167,"cluster":1},{"x":215.9402235086884,"y":237.47997442181955,"cluster":1},{"x":215.9127920823373,"y":166.6429834662163,"cluster":1},{"x":58.26368056343541,"y":233.8615671090896,"cluster":1},{"x":151.2463230121862,"y":40.524023936984534,"cluster":1},{"x":34.05499057542767,"y":236.4692212135835,"cluster":1},{"x":203.0338669466278,"y":221.66081498247465,"cluster":1},{"x":461.0011237017091,"y":266.2845554417521,"cluster":1},{"x":68.35644800363629,"y":477.2301529821135,"cluster":1},{"x":418.233915292622,"y":404.1206309972647,"cluster":1},{"x":401.7561679017409,"y":319.0991627665385,"cluster":1},{"x":388.36408983916147,"y":433.4786023414179,"cluster":1},{"x":309.44352620919597,"y":86.63505060229001,"cluster":1},{"x":137.03346562047406,"y":493.74760251759136,"cluster":1},{"x":200.54626252364864,"y":387.24999649675016,"cluster":1},{"x":364.20835494071184,"y":297.28963262437884,"cluster":1},{"x":39.67031062813872,"y":319.74688902216894,"cluster":1},{"x":10.047930968033963,"y":273.140396077738,"cluster":1},{"x":140.93606523843252,"y":411.25272875662546,"cluster":1},{"x":193.85559869747598,"y":378.80900404558673,"cluster":1},{"x":493.6080547723914,"y":56.80962918860115,"cluster":1},{"x":429.3575889863448,"y":153.9740191415061,"cluster":1},{"x":33.45399360825362,"y":225.53886435640771,"cluster":1},{"x":103.35165493489845,"y":481.750259132785,"cluster":1},{"x":348.0489637009495,"y":110.7018774692855,"cluster":1},{"x":121.6303640361411,"y":446.64003231952654,"cluster":1},{"x":104.3832909937345,"y":394.95269121093435,"cluster":1},{"x":358.0071866863285,"y":19.28483766151943,"cluster":1},{"x":219.33748304599567,"y":260.609401387066,"cluster":1},{"x":121.2596860841416,"y":300.6975515124268,"cluster":1},{"x":459.8555828631443,"y":295.8681906852486,"cluster":1},{"x":404.8534993240674,"y":470.7823344338683,"cluster":1},{"x":179.97792653917247,"y":427.5414572561791,"cluster":1},{"x":117.42143131507281,"y":5.638990987122072,"cluster":1},{"x":254.2871941571597,"y":91.12235459536,"cluster":1},{"x":202.14635541067457,"y":259.4003323205573,"cluster":1},{"x":209.7765380639175,"y":297.761299644521,"cluster":1},{"x":358.43276081474914,"y":491.1655003553188,"cluster":1},{"x":66.66626158608963,"y":469.08550604955764,"cluster":1},{"x":49.55047868983647,"y":353.9694434643583,"cluster":1},{"x":175.27555923970462,"y":290.7012370204195,"cluster":1},{"x":11.295653272395398,"y":464.66776267323144,"cluster":1},{"x":156.6983129735151,"y":117.68859982550062,"cluster":1},{"x":337.1377704263188,"y":179.11859973560337,"cluster":1},{"x":39.73728354203546,"y":418.43245880280506,"cluster":1},{"x":428.8078924017018,"y":214.10718454977263,"cluster":1},{"x":345.31821765961035,"y":490.7281922282166,"cluster":1},{"x":265.83191438313816,"y":394.08603610786975,"cluster":1},{"x":134.4358646146512,"y":182.2599796213188,"cluster":1},{"x":487.12445715475064,"y":312.99299335626256,"cluster":1},{"x":416.5762505754898,"y":158.2689782060619,"cluster":1},{"x":194.43212278706693,"y":341.1612863238498,"cluster":1},{"x":450.5146037609563,"y":286.5130558688731,"cluster":1},{"x":62.406148029125646,"y":1.4645522762718675,"cluster":1},{"x":440.8490297952411,"y":1.2034527103951882,"cluster":1},{"x":27.166680921749265,"y":102.10129791036027,"cluster":1},{"x":275.65905820943277,"y":311.4754733965713,"cluster":1},{"x":6.282908945345287,"y":298.6165470540051,"cluster":1},{"x":445.68532526725073,"y":482.1810212776914,"cluster":1},{"x":126.3970133119721,"y":374.9068738443055,"cluster":1},{"x":326.4856645310663,"y":101.37110096503642,"cluster":1},{"x":90.27817136539633,"y":255.79249055343323,"cluster":1},{"x":338.7941761697648,"y":179.17874739917806,"cluster":1},{"x":69.12311326384436,"y":380.5831060993317,"cluster":1},{"x":100.7336152875149,"y":372.06093639485294,"cluster":1},{"x":194.52102554987255,"y":201.82263623528723,"cluster":1},{"x":101.94801728690152,"y":302.81659008643186,"cluster":1},{"x":129.87275931271344,"y":265.82968237394266,"cluster":1},{"x":211.32187260626716,"y":2.4750795964903807,"cluster":1},{"x":22.572000730760138,"y":317.99619972914047,"cluster":1},{"x":111.25064354133309,"y":231.52635744002475,"cluster":1},{"x":115.83628157559339,"y":18.71496401056068,"cluster":1},{"x":495.78876100903057,"y":220.90364193995555,"cluster":1},{"x":384.718053462896,"y":355.2772747567842,"cluster":1},{"x":493.42543419540885,"y":119.63104500096247,"cluster":1},{"x":308.531256906779,"y":81.11549086948168,"cluster":1},{"x":221.72430046785016,"y":298.1134268512937,"cluster":1},{"x":269.69645416732965,"y":434.36056906423477,"cluster":1},{"x":340.6124965321075,"y":429.6725184525499,"cluster":1},{"x":116.83746311556438,"y":274.8431991871889,"cluster":1},{"x":213.71537662659182,"y":110.12277563961635,"cluster":1},{"x":55.855262532482506,"y":160.3876076380309,"cluster":1},{"x":442.8074887877112,"y":133.93251868689896,"cluster":1},{"x":372.6598543369529,"y":311.5305294028578,"cluster":1},{"x":165.1864309691072,"y":421.8301622898987,"cluster":1},{"x":421.2582920759858,"y":380.64336220429277,"cluster":1},{"x":373.5750026957384,"y":434.5925701885305,"cluster":1},{"x":384.97744765466615,"y":300.8438031530961,"cluster":1},{"x":459.01873403028463,"y":333.19169240684596,"cluster":1},{"x":82.74229534737111,"y":86.05393573425448,"cluster":1},{"x":311.1692839659759,"y":60.47793771679972,"cluster":1},{"x":414.5358348322812,"y":294.09512433692373,"cluster":1},{"x":17.330809409239087,"y":418.14286371133375,"cluster":1},{"x":100.43430346799586,"y":5.805316610579949,"cluster":1},{"x":173.69514508542156,"y":194.83101558897008,"cluster":1},{"x":435.941250066084,"y":16.823202002981,"cluster":1},{"x":251.30295665878316,"y":290.95992508378794,"cluster":1},{"x":198.73685519876923,"y":166.90375326000205,"cluster":1},{"x":225.4418227922542,"y":361.05947635473336,"cluster":1},{"x":122.41384453885314,"y":68.41333140902657,"cluster":1},{"x":406.4286671441691,"y":375.2561062170614,"cluster":1},{"x":69.28881547754357,"y":228.997960557218,"cluster":1},{"x":464.0226012161418,"y":83.90441103804707,"cluster":1},{"x":132.95815434399782,"y":15.326830825204196,"cluster":1},{"x":101.07572139851058,"y":345.30805116278236,"cluster":1},{"x":319.9099007868173,"y":75.28343794717462,"cluster":1},{"x":206.45312000351282,"y":351.9738804968145,"cluster":1},{"x":424.2084978982156,"y":383.0104041856562,"cluster":1},{"x":80.73978804059882,"y":279.90775380645596,"cluster":1},{"x":348.0363775391011,"y":256.8093072413013,"cluster":1},{"x":412.80094724581,"y":28.08709894511193,"cluster":1},{"x":397.7070185536876,"y":238.05546372233587,"cluster":1},{"x":302.8733610175801,"y":235.4353396864616,"cluster":1},{"x":3.6560100263105264,"y":20.007864695873092,"cluster":1},{"x":454.53957028386657,"y":406.3745912703151,"cluster":1},{"x":339.87243133182756,"y":104.67807191543947,"cluster":1},{"x":69.67276247848132,"y":45.347973640281765,"cluster":1},{"x":79.24989108804901,"y":233.76731098389877,"cluster":1},{"x":83.23920239735591,"y":363.5796898950072,"cluster":1},{"x":250.41695573509224,"y":164.08942187224906,"cluster":1},{"x":70.70620016700445,"y":281.78023398271534,"cluster":1},{"x":274.749109602303,"y":230.8677683297676,"cluster":1},{"x":49.72765863296196,"y":34.50660521473501,"cluster":1},{"x":247.4695863185946,"y":243.8276082285355,"cluster":1},{"x":345.7654693551793,"y":459.45118446435305,"cluster":1},{"x":382.01395103002824,"y":113.10114859855496,"cluster":1},{"x":426.3537099113886,"y":190.06041680954968,"cluster":1},{"x":388.1632534754208,"y":260.6205520284733,"cluster":1},{"x":254.82427707512798,"y":148.5736219994658,"cluster":1},{"x":99.84350719897728,"y":273.8949482157183,"cluster":1},{"x":291.48600169934383,"y":58.8242899577921,"cluster":1},{"x":357.9438146252136,"y":402.8507760213825,"cluster":1},{"x":192.4859456380409,"y":321.9606460726329,"cluster":1},{"x":485.02354368420123,"y":474.76038900390824,"cluster":1},{"x":69.88026919047307,"y":441.6192683604487,"cluster":1},{"x":104.35868427677217,"y":463.19206079875903,"cluster":1},{"x":426.8033136508851,"y":394.0249424743122,"cluster":1},{"x":209.42028205761773,"y":438.3852887749239,"cluster":1},{"x":477.04760505674244,"y":168.99188452792342,"cluster":1},{"x":125.58281682049368,"y":346.48848898006224,"cluster":1},{"x":36.85356554722168,"y":477.8660571382967,"cluster":1},{"x":335.62809749003225,"y":61.691817325908474,"cluster":1},{"x":108.25666384020155,"y":470.0749572894951,"cluster":1},{"x":248.44006201358758,"y":416.4460896797901,"cluster":1},{"x":43.95104159716766,"y":85.14107128320761,"cluster":1},{"x":74.17887431695421,"y":464.6795624920952,"cluster":1},{"x":311.3025701777961,"y":73.7668735331449,"cluster":1},{"x":337.1773881009297,"y":469.2073715513504,"cluster":1},{"x":15.88045887135881,"y":55.913816346569334,"cluster":1},{"x":471.8207417724114,"y":243.37422145193267,"cluster":1},{"x":210.67541121876715,"y":341.6746679801858,"cluster":1},{"x":24.750144660440352,"y":230.3791978155539,"cluster":1},{"x":456.0338140369094,"y":188.17809556945264,"cluster":1},{"x":236.87413657350498,"y":343.7021007616044,"cluster":1},{"x":233.26101735069466,"y":16.766172129653334,"cluster":1},{"x":160.87593061324807,"y":412.58408749783325,"cluster":1},{"x":7.833327962830193,"y":101.25015832151809,"cluster":1},{"x":402.172962794968,"y":221.61094438617596,"cluster":1},{"x":240.20693756644525,"y":132.17664635739843,"cluster":1},{"x":329.6148795797764,"y":9.105563249525826,"cluster":1},{"x":35.32358799083738,"y":35.72577158160348,"cluster":1},{"x":288.59858422428977,"y":449.2571804446552,"cluster":1},{"x":406.0863692439187,"y":407.1150883866682,"cluster":1},{"x":359.7343843998796,"y":65.69749269292723,"cluster":1},{"x":381.31551870742265,"y":409.1971235325198,"cluster":1},{"x":224.71456434184387,"y":159.58017643359202,"cluster":1},{"x":162.9929078565733,"y":453.31560614239186,"cluster":1},{"x":429.6158466644271,"y":393.12808447973237,"cluster":1},{"x":108.96508847704303,"y":67.42495934103701,"cluster":1},{"x":208.50996703475514,"y":256.08336731276745,"cluster":1},{"x":113.69886525545594,"y":315.97916322802126,"cluster":1},{"x":468.9613654751778,"y":209.52859360385634,"cluster":1},{"x":225.16943080735936,"y":267.1612545791177,"cluster":1},{"x":255.75889943442675,"y":33.14317644222996,"cluster":1},{"x":488.51001833032933,"y":475.65091806963125,"cluster":1},{"x":182.05818503485912,"y":380.11720050762847,"cluster":1},{"x":30.663432511560323,"y":137.31767423142523,"cluster":1}],"num_clusters":0}