{"title":"coastline-n100-r62-s-6010361733339815459-d3.0100","map_width":500,"map_height":500,"num_leaves":100,"parameters":{"tree_type":"circular","position_type":"sliding","color_distance":"leaves","interval_margin_rectangular":0.2,"interval_margin_circular":0.2,"aversion_centroid_ratio":0.1,"color_difference":0.3,"num_cycles":100,"allowed_outside_interval":false},"tree":{"leaf":false,"id":198,"left":{"leaf":false,"id":196,"left":{"leaf":false,"id":193,"left":{"leaf":false,"id":186,"left":{"leaf":true,"id":8,"label":"8","site_id":8},"right":{"leaf":false,"id":184,"left":{"leaf":false,"id":178,"left":{"leaf":false,"id":139,"left":{"leaf":false,"id":116,"left":{"leaf":true,"id":2,"label":"2","site_id":2},"right":{"leaf":true,"id":1,"label":"1","site_id":1}},"right":{"leaf":true,"id":0,"label":"0","site_id":0}},"right":{"leaf":false,"id":151,"left":{"leaf":true,"id":7,"label":"7","site_id":7},"right":{"leaf":false,"id":148,"left":{"leaf":true,"id":5,"label":"5","site_id":5},"right":{"leaf":true,"id":6,"label":"6","site_id":6}}}},"right":{"leaf":false,"id":120,"left":{"leaf":true,"id":3,"label":"3","site_id":3},"right":{"leaf":true,"id":4,"label":"4","site_id":4}}}},"right":{"leaf":false,"id":190,"left":{"leaf":false,"id":130,"left":{"leaf":false,"id":103,"left":{"leaf":true,"id":35,"label":"35","site_id":35},"right":{"leaf":true,"id":34,"label":"34","site_id":34}},"right":{"leaf":true,"id":32,"label":"32","site_id":32}},"right":{"leaf":false,"id":159,"left":{"leaf":true,"id":33,"label":"33","site_id":33},"right":{"leaf":false,"id":140,"left":{"leaf":true,"id":30,"label":"30","site_id":30},"right":{"leaf":false,"id":119,"left":{"leaf":true,"id":31,"label":"31","site_id":31},"right":{"leaf":true,"id":29,"label":"29","site_id":29}}}}}},"right":{"leaf":false,"id":168,"left":{"leaf":false,"id":161,"left":{"leaf":false,"id":121,"left":{"leaf":true,"id":26,"label":"26","site_id":26},"right":{"leaf":false,"id":106,"left":{"leaf":true,"id":28,"label":"28","site_id":28},"right":{"leaf":true,"id":27,"label":"27","site_id":27}}},"right":{"leaf":false,"id":135,"left":{"leaf":false,"id":107,"left":{"leaf":true,"id":24,"label":"24","site_id":24},"right":{"leaf":true,"id":23,"label":"23","site_id":23}},"right":{"leaf":true,"id":25,"label":"25","site_id":25}}},"right":{"leaf":false,"id":157,"left":{"leaf":true,"id":20,"label":"20","site_id":20},"right":{"leaf":false,"id":100,"left":{"leaf":true,"id":21,"label":"21","site_id":21},"right":{"leaf":true,"id":22,"label":"22","site_id":22}}}}},"right":{"leaf":false,"id":197,"left":{"leaf":false,"id":195,"left":{"leaf":false,"id":194,"left":{"leaf":false,"id":172,"left":{"leaf":false,"id":158,"left":{"leaf":false,"id":153,"left":{"leaf":true,"id":88,"label":"88","site_id":88},"right":{"leaf":true,"id":89,"label":"89","site_id":89}},"right":{"leaf":false,"id":145,"left":{"leaf":true,"id":85,"label":"85","site_id":85},"right":{"leaf":true,"id":86,"label":"86","site_id":86}}},"right":{"leaf":false,"id":134,"left":{"leaf":false,"id":101,"left":{"leaf":true,"id":84,"label":"84","site_id":84},"right":{"leaf":true,"id":83,"label":"83","site_id":83}},"right":{"leaf":true,"id":82,"label":"82","site_id":82}}},"right":{"leaf":false,"id":164,"left":{"leaf":false,"id":152,"left":{"leaf":false,"id":104,"left":{"leaf":true,"id":98,"label":"98","site_id":98},"right":{"leaf":true,"id":99,"label":"99","site_id":99}},"right":{"leaf":false,"id":142,"left":{"leaf":true,"id":97,"label":"97","site_id":97},"right":{"leaf":true,"id":96,"label":"96","site_id":96}}},"right":{"leaf":false,"id":147,"left":{"leaf":false,"id":122,"left":{"leaf":true,"id":95,"label":"95","site_id":95},"right":{"leaf":true,"id":94,"label":"94","site_id":94}},"right":{"leaf":true,"id":93,"label":"93","site_id":93}}}},"right":{"leaf":false,"id":192,"left":{"leaf":false,"id":191,"left":{"leaf":false,"id":187,"left":{"leaf":false,"id":177,"left":{"leaf":false,"id":173,"left":{"leaf":false,"id":165,"left":{"leaf":false,"id":162,"left":{"leaf":false,"id":133,"left":{"leaf":false,"id":118,"left":{"leaf":true,"id":51,"label":"51","site_id":51},"right":{"leaf":true,"id":50,"label":"50","site_id":50}},"right":{"leaf":true,"id":49,"label":"49","site_id":49}},"right":{"leaf":false,"id":150,"left":{"leaf":false,"id":132,"left":{"leaf":true,"id":54,"label":"54","site_id":54},"right":{"leaf":true,"id":53,"label":"53","site_id":53}},"right":{"leaf":true,"id":48,"label":"48","site_id":48}}},"right":{"leaf":true,"id":52,"label":"52","site_id":52}},"right":{"leaf":true,"id":56,"label":"56","site_id":56}},"right":{"leaf":true,"id":55,"label":"55","site_id":55}},"right":{"leaf":false,"id":175,"left":{"leaf":false,"id":123,"left":{"leaf":true,"id":69,"label":"69","site_id":69},"right":{"leaf":true,"id":68,"label":"68","site_id":68}},"right":{"leaf":true,"id":66,"label":"66","site_id":66}}},"right":{"leaf":false,"id":188,"left":{"leaf":false,"id":185,"left":{"leaf":false,"id":182,"left":{"leaf":false,"id":155,"left":{"leaf":true,"id":57,"label":"57","site_id":57},"right":{"leaf":false,"id":105,"left":{"leaf":true,"id":58,"label":"58","site_id":58},"right":{"leaf":true,"id":59,"label":"59","site_id":59}}},"right":{"leaf":false,"id":167,"left":{"leaf":false,"id":108,"left":{"leaf":true,"id":61,"label":"61","site_id":61},"right":{"leaf":true,"id":60,"label":"60","site_id":60}},"right":{"leaf":true,"id":62,"label":"62","site_id":62}}},"right":{"leaf":false,"id":183,"left":{"leaf":false,"id":180,"left":{"leaf":false,"id":126,"left":{"leaf":false,"id":111,"left":{"leaf":false,"id":109,"left":{"leaf":true,"id":72,"label":"72","site_id":72},"right":{"leaf":true,"id":71,"label":"71","site_id":71}},"right":{"leaf":true,"id":70,"label":"70","site_id":70}},"right":{"leaf":true,"id":73,"label":"73","site_id":73}},"right":{"leaf":false,"id":176,"left":{"leaf":false,"id":174,"left":{"leaf":true,"id":65,"label":"65","site_id":65},"right":{"leaf":false,"id":131,"left":{"leaf":false,"id":115,"left":{"leaf":true,"id":67,"label":"67","site_id":67},"right":{"leaf":true,"id":63,"label":"63","site_id":63}},"right":{"leaf":true,"id":64,"label":"64","site_id":64}}},"right":{"leaf":false,"id":171,"left":{"leaf":false,"id":170,"left":{"leaf":false,"id":149,"left":{"leaf":true,"id":81,"label":"81","site_id":81},"right":{"leaf":true,"id":77,"label":"77","site_id":77}},"right":{"leaf":false,"id":129,"left":{"leaf":true,"id":80,"label":"80","site_id":80},"right":{"leaf":true,"id":78,"label":"78","site_id":78}}},"right":{"leaf":true,"id":79,"label":"79","site_id":79}}}},"right":{"leaf":false,"id":166,"left":{"leaf":false,"id":160,"left":{"leaf":true,"id":76,"label":"76","site_id":76},"right":{"leaf":true,"id":75,"label":"75","site_id":75}},"right":{"leaf":true,"id":74,"label":"74","site_id":74}}}},"right":{"leaf":false,"id":169,"left":{"leaf":true,"id":90,"label":"90","site_id":90},"right":{"leaf":false,"id":154,"left":{"leaf":false,"id":117,"left":{"leaf":true,"id":91,"label":"91","site_id":91},"right":{"leaf":true,"id":92,"label":"92","site_id":92}},"right":{"leaf":true,"id":87,"label":"87","site_id":87}}}}},"right":{"leaf":false,"id":181,"left":{"leaf":false,"id":179,"left":{"leaf":false,"id":125,"left":{"leaf":true,"id":16,"label":"16","site_id":16},"right":{"leaf":true,"id":15,"label":"15","site_id":15}},"right":{"leaf":false,"id":138,"left":{"leaf":false,"id":112,"left":{"leaf":true,"id":17,"label":"17","site_id":17},"right":{"leaf":true,"id":19,"label":"19","site_id":19}},"right":{"leaf":true,"id":18,"label":"18","site_id":18}}},"right":{"leaf":false,"id":156,"left":{"leaf":false,"id":113,"left":{"leaf":true,"id":10,"label":"10","site_id":10},"right":{"leaf":true,"id":9,"label":"9","site_id":9}},"right":{"leaf":false,"id":136,"left":{"leaf":false,"id":110,"left":{"leaf":true,"id":14,"label":"14","site_id":14},"right":{"leaf":true,"id":13,"label":"13","site_id":13}},"right":{"leaf":false,"id":124,"left":{"leaf":true,"id":12,"label":"12","site_id":12},"right":{"leaf":true,"id":11,"label":"11","site_id":11}}}}}}},"right":{"leaf":false,"id":189,"left":{"leaf":false,"id":146,"left":{"leaf":false,"id":128,"left":{"leaf":true,"id":46,"label":"46","site_id":46},"right":{"leaf":false,"id":114,"left":{"leaf":true,"id":43,"label":"43","site_id":43},"right":{"leaf":true,"id":45,"label":"45","site_id":45}}},"right":{"leaf":false,"id":144,"left":{"leaf":true,"id":44,"label":"44","site_id":44},"right":{"leaf":true,"id":47,"label":"47","site_id":47}}},"right":{"leaf":false,"id":163,"left":{"leaf":false,"id":102,"left":{"leaf":true,"id":36,"label":"36","site_id":36},"right":{"leaf":true,"id":37,"label":"37","site_id":37}},"right":{"leaf":false,"id":143,"left":{"leaf":true,"id":42,"label":"42","site_id":42},"right":{"leaf":false,"id":141,"left":{"leaf":false,"id":137,"left":{"leaf":true,"id":39,"label":"39","site_id":39},"right":{"leaf":true,"id":40,"label":"40","site_id":40}},"right":{"leaf":false,"id":127,"left":{"leaf":true,"id":38,"label":"38","site_id":38},"right":{"leaf":true,"id":41,"label":"41","site_id":41}}}}}}}},"num_sites":100,"sites":[{"x":18.20972109202847,"y":275.35639007530364,"cluster":1},{"x":22.029401484305478,"y":268.7865117391374,"cluster":1},{"x":23.203570217009464,"y":272.48615510425265,"cluster":1},{"x":35.53557029902181,"y":272.2820571365143,"cluster":1},{"x":36.705000998451006,"y":273.59903460876257,"cluster":1},{"x":36.495315247072426,"y":280.07376123188953,"cluster":1},{"x":41.57502360818727,"y":278.7454615225225,"cluster":1},{"x":46.431051807804565,"y":282.94236317650467,"cluster":1},{"x":53.84904241814174,"y":277.0694343708561,"cluster":1},{"x":60.1203979130661,"y":277.81616219644536,"cluster":1},{"x":65.63856705820626,"y":277.5586750702688,"cluster":1},{"x":71.70405740023617,"y":275.1403750348222,"cluster":1},{"x":69.69653035833431,"y":269.1375134528481,"cluster":1},{"x":77.49803649920995,"y":275.64951967933376,"cluster":1},{"x":79.91024581842937,"y":274.81094947240763,"cluster":1},{"x":83.3580341422548,"y":270.64434982492014,"cluster":1},{"x":90.74356543113349,"y":270.5483328696912,"cluster":1},{"x":97.69473801755963,"y":271.65799068143895,"cluster":1},{"x":98.96848897435659,"y":269.7890102754546,"cluster":1},{"x":108.62869216927524,"y":267.62080699777096,"cluster":1},{"x":113.92605977385641,"y":271.4181557233008,"cluster":1},{"x":117.71359802818127,"y":267.3206180639641,"cluster":1},{"x":118.82319972915565,"y":265.6756607785393,"cluster":1},{"x":124.41507507015965,"y":263.72679107733865,"cluster":1},{"x":129.05184629038345,"y":258.4610161056916,"cluster":1},{"x":130.09899702744386,"y":264.4404006660577,"cluster":1},{"x":138.06796955068694,"y":267.9170791578728,"cluster":1},{"x":142.32675591146034,"y":262.75312999421647,"cluster":1},{"x":146.19756736655103,"y":263.64860241369166,"cluster":1},{"x":156.15226948217799,"y":262.8164329431817,"cluster":1},{"x":152.4364898026159,"y":256.8853456482217,"cluster":1},{"x":159.26595432045852,"y":258.8979793570789,"cluster":1},{"x":162.6268695372608,"y":254.4402031060931,"cluster":1},{"x":166.59465613398248,"y":257.12801209334435,"cluster":1},{"x":172.02994917368173,"y":251.47325902148123,"cluster":1},{"x":177.74513827555936,"y":254.56280932257192,"cluster":1},{"x":182.45714393637468,"y":248.05166131264966,"cluster":1},{"x":190.42562022744988,"y":247.7774250247304,"cluster":1},{"x":195.1234231038128,"y":245.05125870436297,"cluster":1},{"x":202.44847965687416,"y":241.11774313527354,"cluster":1},{"x":202.85330440316477,"y":234.60370759926477,"cluster":1},{"x":212.64883751582533,"y":236.9433248700322,"cluster":1},{"x":208.8875774250599,"y":242.1866501001042,"cluster":1},{"x":221.288249602728,"y":237.26390821209398,"cluster":1},{"x":220.93766369394675,"y":242.2336920482653,"cluster":1},{"x":227.13756284193238,"y":238.73474016744882,"cluster":1},{"x":227.1595223223324,"y":242.60054286017817,"cluster":1},{"x":237.05110872691571,"y":246.9950590017047,"cluster":1},{"x":239.5099848999599,"y":249.0197147814375,"cluster":1},{"x":241.97227553836558,"y":244.21548105810402,"cluster":1},{"x":248.84645920393072,"y":250.0,"cluster":1},{"x":250.49250415812125,"y":246.24581854417366,"cluster":1},{"x":255.3038254095039,"y":239.9125856507369,"cluster":1},{"x":268.14753786313304,"y":245.45228816474733,"cluster":1},{"x":266.19319073508603,"y":249.84817267175887,"cluster":1},{"x":274.6870292024725,"y":251.7773971813132,"cluster":1},{"x":275.89750160020714,"y":245.2285033466306,"cluster":1},{"x":283.25107585085595,"y":249.67476448940585,"cluster":1},{"x":288.4922190163291,"y":245.25325042582395,"cluster":1},{"x":288.5853226370964,"y":243.36200647886952,"cluster":1},{"x":299.39137280283404,"y":239.4786815173164,"cluster":1},{"x":302.0539912430251,"y":242.05897160641598,"cluster":1},{"x":310.40939486762414,"y":244.8672171470821,"cluster":1},{"x":309.89611377753283,"y":239.53280063632766,"cluster":1},{"x":314.1397859799138,"y":233.73906002656852,"cluster":1},{"x":318.6496763361732,"y":230.38346594351714,"cluster":1},{"x":328.95943195262237,"y":234.2658684696452,"cluster":1},{"x":325.4794243537085,"y":235.75177607075523,"cluster":1},{"x":333.0207284590492,"y":241.24956039993836,"cluster":1},{"x":339.6667572921563,"y":241.8128016643031,"cluster":1},{"x":346.93642620627736,"y":246.47558109304168,"cluster":1},{"x":345.2689649951299,"y":250.03999774997445,"cluster":1},{"x":348.0895504696537,"y":254.29209174073804,"cluster":1},{"x":359.6643142670382,"y":248.22939039775534,"cluster":1},{"x":360.9281786198374,"y":246.574849630203,"cluster":1},{"x":368.72699371697814,"y":248.61655518651227,"cluster":1},{"x":366.3411411669935,"y":246.4745677957354,"cluster":1},{"x":375.5114915203229,"y":246.16234171907237,"cluster":1},{"x":383.7976030310348,"y":242.14745546554053,"cluster":1},{"x":380.42547168267635,"y":244.53341967754315,"cluster":1},{"x":385.85438753812764,"y":246.18029497805557,"cluster":1},{"x":398.05754184656934,"y":247.93179248075813,"cluster":1},{"x":400.6546869053094,"y":250.7427345681782,"cluster":1},{"x":405.22156993414734,"y":244.59510599655727,"cluster":1},{"x":405.7061357345149,"y":248.4253396485861,"cluster":1},{"x":417.1399408503441,"y":244.00627419079308,"cluster":1},{"x":418.098159392423,"y":240.33742918091232,"cluster":1},{"x":425.0053048048253,"y":241.58592861103145,"cluster":1},{"x":424.29919233763064,"y":235.69525126493116,"cluster":1},{"x":436.1034447147985,"y":234.0821623584265,"cluster":1},{"x":436.55306975400254,"y":240.00445947327216,"cluster":1},{"x":444.8671187034377,"y":242.05684231152222,"cluster":1},{"x":442.158843346642,"y":241.1634047432457,"cluster":1},{"x":452.3260105462348,"y":238.90412731295297,"cluster":1},{"x":455.1373250805826,"y":234.4192641707069,"cluster":1},{"x":457.189906721467,"y":236.46478702665516,"cluster":1},{"x":463.5284882315983,"y":239.6534922323746,"cluster":1},{"x":469.42463407206975,"y":240.04753944729364,"cluster":1},{"x":477.6948444305903,"y":245.90870063886555,"cluster":1},{"x":482.37235288012533,"y":243.90123697130636,"cluster":1}],"num_clusters":0}